easyarduino/__init__.py
easyarduino/arduino_controller.py
easyarduino/utils.py
easyarduino-0.3.dist-info/LICENSE
easyarduino-0.3.dist-info/METADATA
easyarduino-0.3.dist-info/WHEEL
easyarduino-0.3.dist-info/top_level.txt
easyarduino-0.3.dist-info/RECORD
