Metadata-Version: 2.1
Name: easyarduino
Version: 0.3
Summary: A simple and easy-to-use Arduino control library using PyFirmata
Home-page: https://github.com/IMApurbo/easyarduino
Author: AKM Korishee Apurbo
Author-email: bandinvisible8@gmail.com
Classifier: Programming Language :: Python :: 3
Classifier: License :: OSI Approved :: MIT License
Classifier: Operating System :: OS Independent
Requires-Python: >=3.6
License-File: LICENSE
Requires-Dist: pyfirmata
Requires-Dist: pyserial
